mcpackutil/__init__.py
mcpackutil/cli.py
mcpackutil/dotminecraft.py
mcpackutil/extractor.py
mcpackutil/is_pack.py
mcpackutil-1.0.3.dist-info/LICENSE
mcpackutil-1.0.3.dist-info/METADATA
mcpackutil-1.0.3.dist-info/WHEEL
mcpackutil-1.0.3.dist-info/entry_points.txt
mcpackutil-1.0.3.dist-info/top_level.txt
mcpackutil-1.0.3.dist-info/RECORD
